rocket/__init__.py
rocket/packet.py
rocket/rocket.py
rocket_client-0.1.0.dist-info/METADATA
rocket_client-0.1.0.dist-info/WHEEL
rocket_client-0.1.0.dist-info/top_level.txt
rocket_client-0.1.0.dist-info/RECORD
