Metadata-Version: 2.1
Name: rocket-client
Version: 0.1.0
Summary: rocket protocol client
Home-page: https://github.com/sectasy0/rocket
Author: sectasy
Author-email: sectasy0@gmail.com
License: MIT License
Keywords: rocket,rcon alternative
Requires-Dist: cryptography (==39.0.1)
